stc/__init__.py
stc-0.3.2.dist-info/LICENSE
stc-0.3.2.dist-info/METADATA
stc-0.3.2.dist-info/WHEEL
stc-0.3.2.dist-info/top_level.txt
stc-0.3.2.dist-info/RECORD
