Metadata-Version: 2.1
Name: stc
Version: 0.3.2
Summary: Sparse Tensor Classifier
Home-page: https://sparsetensorclassifier.org
Author: Emanuele Guidotti
Author-email: emanuele.guidotti@unine.ch
License: GPLv3
Project-URL: Documentation, https://sparsetensorclassifier.org/docs.html
Project-URL: Source, https://github.com/sparsetensorclassifier
Project-URL: Tracker, https://github.com/sparsetensorclassifier/stc/issues
Classifier: Development Status :: 5 - Production/Stable
Classifier: Intended Audience :: Science/Research
Classifier: License :: OSI Approved :: GNU General Public License v3 (GPLv3)
Classifier: Operating System :: OS Independent
Classifier: Programming Language :: Python :: 3
Classifier: Programming Language :: Python :: 3.6
Classifier: Programming Language :: Python :: 3.7
Classifier: Programming Language :: Python :: 3.8
Classifier: Programming Language :: Python :: 3.9
Classifier: Topic :: Database
Classifier: Topic :: Scientific/Engineering
Classifier: Topic :: Scientific/Engineering :: Artificial Intelligence
Requires-Python: >=3
License-File: LICENSE
Requires-Dist: numpy
Requires-Dist: pandas
Requires-Dist: sqlalchemy
